{
  "trackedEntityInstances": [
    {
      "lastUpdated": "2019-01-10T13:40:28.592",
      "trackedEntityType": "nEenWmSyUEp",
      "createdAtClient": "2019-01-22T18:38:15.845",
      "lastUpdatedAtClient": "2019-01-22T18:38:15.845",
      "created": "2019-01-10T13:40:27.987",
      "orgUnit": "DiszpKrYNg8",
      "trackedEntityInstance": "nWrB0TfWlvh",
      "deleted": false,
      "relationships": [
        {
          "lastUpdated": "2019-02-07T08:06:28.369",
          "created": "2019-02-07T08:06:28.369",
          "relationshipName": "Lab Sample to Person",
          "relationshipType": "V2kkHafqs8G",
          "relationship": "AJOytZW7OaI",
          "from": {
            "trackedEntityInstance": {
              "trackedEntityInstance": "nWrB0TfWlvh"
            }
          },
          "to": {
            "trackedEntityInstance": {
              "trackedEntityInstance": "nWrB0TfWlvD"
            }
          }
        },
        {
          "lastUpdated": "2018-02-07T08:06:28.369",
          "created": "2018-02-07T08:06:28.369",
          "relationshipName": "Prescription to Person",
          "relationshipType": "o51cUNONthg",
          "relationship": "AJOytZW7OaB",
          "from": {
            "trackedEntityInstance": {
              "trackedEntityInstance": "nWrB0TfWlvD"
            }
          },
          "to": {
            "trackedEntityInstance": {
              "trackedEntityInstance": "nWrB0TfWlvh"
            }
          }
        }
      ],
      "attributes": [
        {
          "lastUpdated": "2019-01-10T13:40:28.000",
          "created": "2019-01-10T13:40:28.000",
          "attribute": "cejWyOfXge6",
          "value": "4081507"
        }
      ],
      "enrollments": [
        {
          "created": "2019-01-10T13:40:28.322",
          "orgUnit": "DiszpKrYNg8",
          "program": "lxAQ7Zs9VYR",
          "enrollment": "enroll1",
          "trackedEntityInstance": "nWrB0TfWlvh",
          "lastUpdated": "2019-01-10T13:40:28.718",
          "enrollmentDate": "2019-01-10T00:00:00.000",
          "followup": true,
          "deleted": false,
          "incidentDate": "2019-01-10T00:00:00.000",
          "status": "ACTIVE",
          "geometry": {
            "type": "Polygon",
            "coordinates": [
              [
                [
                  -12.408816,
                  9.135595
                ],
                [
                  -12.018653,
                  9.411972
                ],
                [
                  -11.337243,
                  9.184383
                ],
                [
                  -12.408816,
                  9.135595
                ]
              ]
            ]
          },
          "notes": [
            {
              "note": "enrollmentNote1",
              "storedDate": "2018-03-19T15:20:55.058",
              "storedBy": "android",
              "value": "TEI enrollment note 1"
            },
            {
              "note": "enrollmentNote2",
              "storedDate": "2018-03-19T15:20:55.058",
              "storedBy": "android",
              "value": "TEI enrollment note 2"
            }
          ],
          "events": [
            {
              "programStage": "dBwrot7S420",
              "storedBy": "system",
              "orgUnit": "DiszpKrYNg8",
              "dueDate": "2015-05-01T00:00:00.000",
              "program": "lxAQ7Zs9VYR",
              "href": "https://play.dhis2.org/demo/api/events/hnaWBxMw5j3",
              "event": "event1",
              "status": "COMPLETED",
              "eventDate": "2015-05-01T00:00:00.000",
              "orgUnitName": "Ngelehun CHC",
              "created": "2015-09-08T21:40:22.000",
              "completedDate": "2019-01-15T00:00:00.000",
              "lastUpdated": "2015-11-15T14:55:22.995",
              "completedBy": "system",
              "enrollment": "enroll1",
              "deleted": false,
              "coordinate": {
                "latitude": 0.0,
                "longitude": 0.0
              },
              "dataValues": [
                {
                  "lastUpdated": "2017-12-12T07:35:12.167",
                  "storedBy": "android",
                  "created": "2017-12-12T07:35:12.166",
                  "dataElement": "g9eOBujte1U",
                  "value": "false",
                  "providedElsewhere": false
                }
              ],
              "notes": [
                {
                  "note": "teiNote1",
                  "storedDate": "2018-03-19T15:20:55.058",
                  "storedBy": "android",
                  "value": "TEI event note 1"
                },
                {
                  "note": "teiNote2",
                  "storedDate": "2018-03-19T15:20:55.058",
                  "storedBy": "android",
                  "value": "TEI event note 2"
                }
              ]
            }
          ]
        }
      ],
      "programOwners": [
        {
          "ownerOrgUnit": "DiszpKrYNg8",
          "program": "lxAQ7Zs9VYR",
          "trackedEntityInstance": "nWrB0TfWlvh"
        }
      ]
    },
    {
      "lastUpdated": "2018-01-10T13:40:28.592",
      "trackedEntityType": "nEenWmSyUEp",
      "createdAtClient": "2018-01-22T18:38:15.845",
      "lastUpdatedAtClient": "2018-01-22T18:38:15.845",
      "coordinates": "[9,9]",
      "created": "2018-01-10T13:40:27.987",
      "orgUnit": "DiszpKrYNg8",
      "trackedEntityInstance": "nWrB0TfWlvD",
      "deleted": false,
      "geometry": {
        "type": "Point",
        "coordinates": [
          9.0,
          9.0
        ]
      },
      "relationships": [
        {
          "lastUpdated": "2018-02-07T08:06:28.369",
          "created": "2018-02-07T08:06:28.369",
          "relationshipName": "Prescription to Person",
          "relationshipType": "o51cUNONthg",
          "relationship": "AJOytZW7OaB",
          "from": {
            "trackedEntityInstance": {
              "trackedEntityInstance": "nWrB0TfWlvD"
            }
          },
          "to": {
            "trackedEntityInstance": {
              "trackedEntityInstance": "nWrB0TfWlvh"
            }
          }
        },
        {
          "lastUpdated": "2019-02-07T08:06:28.369",
          "created": "2019-02-07T08:06:28.369",
          "relationshipName": "Lab Sample to Person",
          "relationshipType": "V2kkHafqs8G",
          "relationship": "AJOytZW7OaI",
          "from": {
            "trackedEntityInstance": {
              "trackedEntityInstance": "nWrB0TfWlvh"
            }
          },
          "to": {
            "trackedEntityInstance": {
              "trackedEntityInstance": "nWrB0TfWlvD"
            }
          }
        }
      ],
      "attributes": [
        {
          "lastUpdated": "2018-01-10T13:40:28.000",
          "created": "2018-01-10T13:40:28.000",
          "attribute": "cejWyOfXge6",
          "value": "654321"
        },
        {
          "lastUpdated": "2017-01-10T13:40:28.000",
          "created": "2017-01-10T13:40:28.000",
          "attribute": "aejWyOfXge6",
          "value": "123456"
        }
      ],
      "enrollments": [
        {
          "created": "2018-01-10T13:40:28.322",
          "orgUnit": "DiszpKrYNg8",
          "program": "lxAQ7Zs9VYR",
          "enrollment": "enroll2",
          "trackedEntityInstance": "nWrB0TfWlvD",
          "lastUpdated": "2018-01-10T13:40:28.718",
          "createdAtClient": "2018-01-08T13:40:28.718",
          "lastUpdatedAtClient": "2018-01-11T13:40:28.718",
          "enrollmentDate": "2018-01-10T00:00:00.000",
          "followup": false,
          "deleted": false,
          "incidentDate": "2018-01-10T00:00:00.000",
          "status": "ACTIVE",
          "notes": [
            {
              "note": "enrollmentNote3",
              "storedDate": "2018-03-19T15:20:55.058",
              "storedBy": "android",
              "value": "TEI enrollment note 3"
            },
            {
              "note": "enrollmentNote4",
              "storedDate": "2018-03-19T15:20:55.058",
              "storedBy": "android",
              "value": "TEI enrollmnet note 4"
            }
          ],
          "coordinate": {
            "latitude": 2.6,
            "longitude": 4.1
          },
          "events": [
            {
              "programStage": "dBwrot7S420",
              "storedBy": "system",
              "orgUnit": "DiszpKrYNg8",
              "dueDate": "2016-05-01T00:00:00.000",
              "program": "lxAQ7Zs9VYR",
              "href": "https://play.dhis2.org/demo/api/events/hnaWBxMw5j3",
              "event": "event2",
              "status": "SCHEDULE",
              "orgUnitName": "Ngelehun CHC",
              "created": "2016-09-08T21:40:22.000",
              "completedDate": "2015-11-15T00:00:00.000",
              "lastUpdated": "2016-11-15T14:55:22.995",
              "completedBy": "system",
              "enrollment": "enroll2",
              "deleted": false,
              "coordinate": {
                "latitude": 0.0,
                "longitude": 0.0
              },
              "dataValues": [],
              "notes": [
                {
                  "note": "teiNote3",
                  "storedDate": "2016-11-11T15:20:55.058",
                  "storedBy": "android",
                  "value": "TEI event note 3"
                }
              ]
            }
          ]
        }
      ],
      "programOwners": [
        {
          "ownerOrgUnit": "DiszpKrYNg8",
          "program": "lxAQ7Zs9VYR",
          "trackedEntityInstance": "nWrB0TfWlvD"
        }
      ]
    }
  ]
}