{
  "event": "EsHa0edW6uY",
  "status": "COMPLETED",
  "program": "IpHINAT79UW",
  "programStage": "A03MvHHogjR",
  "enrollment": "KpknKHptul0",
  "orgUnit": "DiszpKrYNg8",
  "orgUnitName": "Ngelehun CHC",
  "relationships": [],
  "occurredAt": "2022-01-10T00:00:00.000",
  "scheduledAt": "2022-09-28T00:00:00.000",
  "storedBy": "admin",
  "followup": false,
  "deleted": false,
  "createdAt": "2018-01-20T10:44:03.222",
  "createdAtClient": "2018-01-20T10:44:03.222",
  "updatedAt": "2022-09-28T14:23:29.021",
  "updatedAtClient": "2022-09-28T14:23:29.021",
  "attributeOptionCombo": "HllvX50cXC0",
  "attributeCategoryOptions": "xYerKDKCefk",
  "completedAt": "2022-01-20T00:00:00.000",
  "geometry": {
    "type": "Point",
    "coordinates": [
      -11.618041992187502,
      9.508486893003065
    ]
  },
  "assignedUser": {
    "uid": "DXyJmlo9rge",
    "username": "android",
    "firstName": "John",
    "surname": "Barnes"
  },
  "updatedBy": {
    "uid": "xE7jOejl9FI",
    "username": "admin",
    "firstName": "John",
    "surname": "Traore"
  },
  "dataValues": [
    {
      "createdAt": "2017-01-20T10:44:03.231",
      "updatedAt": "2022-09-28T14:23:29.016",
      "providedElsewhere": false,
      "dataElement": "UXz7xuGCEhU",
      "value": "4322",
      "updatedBy": {
        "uid": "xE7jOejl9FI",
        "username": "admin",
        "firstName": "John",
        "surname": "Traore"
      }
    },
    {
      "createdAt": "2022-09-28T14:12:38.130",
      "updatedAt": "2022-09-28T14:23:29.016",
      "providedElsewhere": false,
      "dataElement": "a3kGcGDCuk6",
      "value": "2",
      "createdBy": {
        "uid": "xE7jOejl9FI",
        "username": "admin",
        "firstName": "John",
        "surname": "Traore"
      },
      "updatedBy": {
        "uid": "xE7jOejl9FI",
        "username": "admin",
        "firstName": "John",
        "surname": "Traore"
      }
    }
  ],
  "notes": []
}