{
  "httpStatus": "Conflict",
  "httpStatusCode": 409,
  "status": "ERROR",
  "message": "An error occurred, please check import summary.",
  "response": {
    "responseType": "ImportSummaries",
    "status": "ERROR",
    "imported": 0,
    "updated": 0,
    "deleted": 0,
    "ignored": 2,
    "importOptions": {
      "idSchemes": {},
      "dryRun": false,
      "async": false,
      "importStrategy": "SYNC",
      "mergeMode": "REPLACE",
      "reportMode": "FULL",
      "skipExistingCheck": false,
      "sharing": false,
      "skipNotifications": false,
      "skipAudit": false,
      "datasetAllowsPeriods": false,
      "strictPeriods": false,
      "strictDataElements": false,
      "strictCategoryOptionCombos": false,
      "strictAttributeOptionCombos": false,
      "strictOrganisationUnits": false,
      "requireCategoryOptionCombo": false,
      "requireAttributeOptionCombo": false,
      "skipPatternValidation": false,
      "ignoreEmptyCollection": false,
      "force": false,
      "firstRowIsHeader": true,
      "skipLastUpdated": false,
      "mergeDataValues": false,
      "skipCache": false
    },
    "importSummaries": [
      {
        "responseType": "ImportSummary",
        "status": "ERROR",
        "description": "Program is not assigned to this Organisation Unit: ABJTilhqOCW",
        "importCount": {
          "imported": 0,
          "updated": 0,
          "ignored": 1,
          "deleted": 0
        },
        "conflicts": [],
        "reference": "STPIK5YTi4f"
      },
      {
        "responseType": "ImportSummary",
        "status": "ERROR",
        "description": "Program is not assigned to this Organisation Unit: ABJTilhqOCW",
        "importCount": {
          "imported": 0,
          "updated": 0,
          "ignored": 1,
          "deleted": 0
        },
        "conflicts": [],
        "reference": "sjSyAZLTOfK"
      }
    ],
    "total": 2
  }
}