{
  "httpStatus": "OK",
  "httpStatusCode": 200,
  "status": "OK",
  "message": "Import was successful.",
  "response": {
    "responseType": "ImportSummaries",
    "status": "SUCCESS",
    "imported": 1,
    "updated": 0,
    "deleted": 0,
    "ignored": 0,
    "importOptions": {
      "idSchemes": {},
      "dryRun": false,
      "async": false,
      "importStrategy": "SYNC",
      "mergeMode": "REPLACE",
      "reportMode": "FULL",
      "skipExistingCheck": false,
      "sharing": false,
      "skipNotifications": false,
      "skipAudit": false,
      "datasetAllowsPeriods": false,
      "strictPeriods": false,
      "strictDataElements": false,
      "strictCategoryOptionCombos": false,
      "strictAttributeOptionCombos": false,
      "strictOrganisationUnits": false,
      "requireCategoryOptionCombo": false,
      "requireAttributeOptionCombo": false,
      "skipPatternValidation": false,
      "ignoreEmptyCollection": false,
      "force": false,
      "firstRowIsHeader": true,
      "skipLastUpdated": false,
      "mergeDataValues": false,
      "skipCache": false
    },
    "importSummaries": [
      {
        "responseType": "ImportSummary",
        "status": "SUCCESS",
        "importOptions": {
          "idSchemes": {},
          "dryRun": false,
          "async": false,
          "importStrategy": "SYNC",
          "mergeMode": "REPLACE",
          "reportMode": "FULL",
          "skipExistingCheck": false,
          "sharing": false,
          "skipNotifications": false,
          "skipAudit": false,
          "datasetAllowsPeriods": false,
          "strictPeriods": false,
          "strictDataElements": false,
          "strictCategoryOptionCombos": false,
          "strictAttributeOptionCombos": false,
          "strictOrganisationUnits": false,
          "requireCategoryOptionCombo": false,
          "requireAttributeOptionCombo": false,
          "skipPatternValidation": false,
          "ignoreEmptyCollection": false,
          "force": false,
          "firstRowIsHeader": true,
          "skipLastUpdated": false,
          "mergeDataValues": false,
          "skipCache": false
        },
        "importCount": {
          "imported": 1,
          "updated": 0,
          "ignored": 0,
          "deleted": 0
        },
        "conflicts": [],
        "reference": "n62vX8eLI6R",
        "href": "https://play.dhis2.org/android-dev/api/events/n62vX8eLI6R"
      }
    ],
    "total": 1
  }
}