{
  "pager": {
    "page": 1,
    "pageCount": 1,
    "total": 3,
    "pageSize": 50
  }, "dataElements": [{
  "code": "codedata",
  "lastUpdated": "2018-02-06T23:00:03.766",
  "id": "SKPMfGShCt5",
  "href": "http://127.0.0.1:8080/api/dataElements/SKPMfGShCt5",
  "created": "2018-02-06T23:00:03.766",
  "name": "name test",
  "shortName": "short name test",
  "aggregationType": "SUM",
  "domainType": "AGGREGATE",
  "displayName": "name test",
  "publicAccess": "rw------",
  "description": "desc",
  "displayShortName": "short name test",
  "externalAccess": false,
  "valueType": "NUMBER",
  "formName": "form name",
  "displayDescription": "desc",
  "dimensionItem": "SKPMfGShCt5",
  "displayFormName": "form name",
  "zeroIsSignificant": false,
  "optionSetValue": false,
  "dimensionItemType": "DATA_ELEMENT",
  "access": {
    "read": true,
    "update": true,
    "externalize": false,
    "delete": true,
    "write": true,
    "manage": true
  },
  "categoryCombo": {
    "id": "p0KPaWEg3cf"
  },
  "lastUpdatedBy": {
    "id": "xE7jOejl9FI"
  },
  "user": {
    "id": "xE7jOejl9FI"
  },
  "dataSetElements": [],
  "translations": [],
  "userGroupAccesses": [],
  "dataElementGroups": [],
  "attributeValues": [],
  "userAccesses": [],
  "legendSets": [],
  "aggregationLevels": []
}]
}
